README
setup.py
subdownloader-lite
subdownloader/__init__.py
subdownloader/subDownLib/__init__.py
subdownloader/subDownLib/downloadManager.py
subdownloader/subDownLib/matrix.py
subdownloader/subDownLib/opensubtitles.py
subdownloader/subDownLib/subtitlErrorHandler.py
subdownloader/util/__init__.py
subdownloader/util/version.py
subdownloaderlite.egg-info/PKG-INFO
subdownloaderlite.egg-info/SOURCES.txt
subdownloaderlite.egg-info/dependency_links.txt
subdownloaderlite.egg-info/top_level.txt