Metadata-Version: 1.0
Name: subdownloaderlite
Version: 0.0.7
Summary: A simple command line tool to search and download subtitles from opensubtitles.org 
Home-page: http://www.melillo.me/subdownloader
Author: Gabriel Melillo
Author-email: gabriel@melillo.me
License: BSD
Platform: UNKNOWN
